bbg/__init__.py
bbg/_globals.py
bbg/_metadata.py
bbg/_secrets.py
bbg/metadata.py
bbg/secrets.py
bbg/sql/__init__.py
bbg/sql/_hana.py
bbg/sql/_jaydebeapi.py
bbg/sql/_pyspark.py
bbg/sql/_snowflake.py
bbg/sql/_typing.py
bbg/sql/_watermarks.py
bbg/sql/typing.py
bbg_databricks-0.7.3.dist-info/LICENSE
bbg_databricks-0.7.3.dist-info/METADATA
bbg_databricks-0.7.3.dist-info/WHEEL
bbg_databricks-0.7.3.dist-info/top_level.txt
bbg_databricks-0.7.3.dist-info/RECORD
